{
  "document_id": "IRS-2026-0133-0001",
  "docket_id": "IRS-2026-0133",
  "agency_id": "IRS",
  "agency_name": "Internal Revenue Service",
  "title": "Section 45Z Clean Fuel Production Credit",
  "document_type": "Proposed Rule",
  "posted_date": "2026-02-04T05:00:00Z",
  "comment_end_date": "2026-04-07T03:59:59Z",
  "pass_1_score": 9,
  "pass_2_score": 3,
  "pass_1_scaled": 0.7063970219823053,
  "pass_2_scaled": 0.6982911831727412,
  "combined_score": 0.7043705622799142,
  "score_total": 12,
  "pass_2_rule_type": "TECHNICAL",
  "pass_2_risk_band": "moderate_analytical_concern",
  "pass_2_flags": [
    "facility_impacts_without_representative_facility",
    "missing_cost_per_unit_signal",
    "missing_supporting_analysis_references"
  ],
  "rule_text_chars": 334576,
  "rule_text_sources": [
    "https://www.federalregister.gov/documents/full_text/html/2026/02/04/2026-02246.html"
  ],
  "supporting_related_material_count": 0,
  "supporting_docs_error": null,
  "supporting_related_material": [],
  "summary_available": false,
  "raw_summary_available": false
}